livekit/__init__.py
livekit/_utils.py
livekit/analytics.py
livekit/egress.py
livekit/ingress.py
livekit/internal.py
livekit/models.py
livekit/room.py
livekit/rpc_internal.py
livekit/rtc.py
livekit/twirp.py
livekit/webhook.py
livekit/_proto/__init__.py
livekit/_proto/livekit_analytics_pb2.py
livekit/_proto/livekit_analytics_pb2.pyi
livekit/_proto/livekit_egress_pb2.py
livekit/_proto/livekit_egress_pb2.pyi
livekit/_proto/livekit_ingress_pb2.py
livekit/_proto/livekit_ingress_pb2.pyi
livekit/_proto/livekit_internal_pb2.py
livekit/_proto/livekit_internal_pb2.pyi
livekit/_proto/livekit_models_pb2.py
livekit/_proto/livekit_models_pb2.pyi
livekit/_proto/livekit_room_pb2.py
livekit/_proto/livekit_room_pb2.pyi
livekit/_proto/livekit_rpc_internal_pb2.py
livekit/_proto/livekit_rpc_internal_pb2.pyi
livekit/_proto/livekit_rtc_pb2.py
livekit/_proto/livekit_rtc_pb2.pyi
livekit/_proto/livekit_webhook_pb2.py
livekit/_proto/livekit_webhook_pb2.pyi
livekit/_twirp/__init__.py
livekit/_twirp/livekit_analytics_twirp.py
livekit/_twirp/livekit_egress_twirp.py
livekit/_twirp/livekit_ingress_twirp.py
livekit/_twirp/livekit_internal_twirp.py
livekit/_twirp/livekit_models_twirp.py
livekit/_twirp/livekit_room_twirp.py
livekit/_twirp/livekit_rpc_internal_twirp.py
livekit/_twirp/livekit_rtc_twirp.py
livekit/_twirp/livekit_webhook_twirp.py
livekit_server_sdk_python-1.0.0.dist-info/LICENCE
livekit_server_sdk_python-1.0.0.dist-info/METADATA
livekit_server_sdk_python-1.0.0.dist-info/WHEEL
livekit_server_sdk_python-1.0.0.dist-info/top_level.txt
livekit_server_sdk_python-1.0.0.dist-info/RECORD
