Metadata-Version: 2.1
Name: livekit-server-sdk-python
Version: 1.0.0
Summary: Livekit Server SDK for Python
Home-page: https://github.com/tradablebits/livekit-server-sdk-python
Author: Tradable Bits
Author-email: dev@tradablebits.com
License: Apache-2.0
Project-URL: Bug Tracker, https://github.com/tradablebits/livekit-server-sdk-python/issues
Classifier: License :: OSI Approved :: Apache Software License
Classifier: Operating System :: OS Independent
Classifier: Programming Language :: Python
Classifier: Programming Language :: Python :: 3
Classifier: Programming Language :: Python :: 3 :: Only
Classifier: Programming Language :: Python :: 3.7
Classifier: Programming Language :: Python :: 3.8
Classifier: Programming Language :: Python :: 3.9
Classifier: Programming Language :: Python :: 3.10
Requires-Python: >=3.7
Provides-Extra: dev
License-File: LICENCE
